string_editing_tools/__init__.py
string_editing_tools/functions.py
string_editing_tools-0.1.0.dist-info/METADATA
string_editing_tools-0.1.0.dist-info/WHEEL
string_editing_tools-0.1.0.dist-info/entry_points.txt
string_editing_tools-0.1.0.dist-info/top_level.txt
string_editing_tools-0.1.0.dist-info/RECORD
