Metadata-Version: 2.1
Name: string_editing_tools
Version: 0.1.0
Summary: A collection of utilities for editing and manipulating strings
Author: Milan
Author-email: magnatoshadow@gmail.com
